activation_code_generator.py
config.py
debug_stats_display.py
demo_license.py
file_downloader.py
license_cli.py
license_manager.py
main.py
mcp_server.py
multi_account_example.py
quick_fix_test.py
quick_test.py
random_item_script.py
simple_script.py
static_file_manager.py
template_loader.py
test_account_management.py
test_analyze_functionality.py
test_analyze_integration.py
test_basic.py
test_collect_function.py
test_content_functionality.py
test_content_integration.py
test_cookies_history.py
test_error_flow.py
test_image_preview.py
test_like_collect_display_fix.py
test_like_collect_return_format.py
test_like_function.py
test_login_check.py
test_login_wait.py
test_mcp_server.py
test_multi_account.py
test_publish_fix.py
test_publish_simple.py
test_search_functionality.py
test_search_integration.py
test_success_status_fix.py
test_timeout_improvements.py
unti.py
xiaohongshu_mcp.py
xiaohongshu_tools.py
adapters/__init__.py
adapters/xiaohongshu_adapter.py
scripts/publish.py
static/__init__.py
static/js/__init__.py
static/js/account_manage.js
templates/__init__.py
templates/account_manage.html
templates/activate.html
tools/__init__.py
tools/account_management_tool.py
tools/analysis_tool.py
tools/base_tool.py
tools/comment_post_tool.py
tools/comments_tool.py
tools/content_tool.py
tools/monitor_tool.py
tools/publish_tool.py
tools/search_tool.py
tools/timeout_diagnostic_tool.py
tools/tool_manager.py
xiaohongshu_automation-2.0.9.dist-info/METADATA
xiaohongshu_automation-2.0.9.dist-info/WHEEL
xiaohongshu_automation-2.0.9.dist-info/entry_points.txt
xiaohongshu_automation-2.0.9.dist-info/licenses/LICENSE
xiaohongshu_automation-2.0.9.dist-info/licenses/LICENSE_USAGE.md
xiaohongshu_automation-2.0.9.dist-info/licenses/license.backup
xiaohongshu_automation-2.0.9.dist-info/licenses/license_cli.py
xiaohongshu_automation-2.0.9.dist-info/licenses/license_manager.py
xiaohongshu_automation-2.0.9.dist-info/RECORD
