Metadata-Version: 2.4
Name: xiaohongshu-automation
Version: 2.0.9
Summary: 基于 Model Context Protocol (MCP) 的小红书自动化解决方案
Project-URL: Homepage, https://github.com/A1721/xiaohongshu-automation
Project-URL: Repository, https://github.com/A1721/xiaohongshu-automation.git
Project-URL: Issues, https://github.com/A1721/xiaohongshu-automation/issues
Author: A1721
License-Expression: MIT
License-File: LICENSE
License-File: LICENSE_USAGE.md
License-File: license.backup
License-File: license_cli.py
License-File: license_manager.py
Keywords: automation,fastapi,mcp,xiaohongshu
Classifier: Development Status :: 4 - Beta
Classifier: Intended Audience :: Developers
Classifier: License :: OSI Approved :: MIT License
Classifier: Programming Language :: Python :: 3.10
Classifier: Programming Language :: Python :: 3.11
Classifier: Programming Language :: Python :: 3.12
Classifier: Programming Language :: Python :: 3.13
Classifier: Topic :: Internet :: WWW/HTTP :: WSGI :: Application
Classifier: Topic :: Software Development :: Libraries :: Python Modules
Requires-Python: >=3.10
Requires-Dist: fastapi>=0.104.0
Requires-Dist: httpx>=0.25.0
Requires-Dist: mcp>=1.0.0
Requires-Dist: pydantic>=2.0.0
Requires-Dist: requests
Requires-Dist: selenium
Requires-Dist: uvicorn>=0.24.0
Requires-Dist: webdriver-manager
Provides-Extra: dev
Requires-Dist: black; extra == 'dev'
Requires-Dist: isort; extra == 'dev'
Requires-Dist: mypy; extra == 'dev'
Requires-Dist: pytest-asyncio>=0.21.0; extra == 'dev'
Requires-Dist: pytest>=7.0.0; extra == 'dev'
